setup.py
Thinkpol/__init__.py
Thinkpol/agent.py
Thinkpol/miniture.py
Thinkpol/port.py
Thinkpol/supervisor.py
Thinkpol/telescreen.py
Thinkpol.egg-info/PKG-INFO
Thinkpol.egg-info/SOURCES.txt
Thinkpol.egg-info/dependency_links.txt
Thinkpol.egg-info/requires.txt
Thinkpol.egg-info/top_level.txt