Metadata-Version: 1.0
Name: Thinkpol
Version: 0.1.0
Summary: Helper classes to write monitoring part in distributed applications
Home-page: https://github.com/Tefx/Thinkpol
Author: Zhu Zhaomeng
Author-email: zhaomeng.zhu@gmail.com
License: UNKNOWN
Platform: UNKNOWN
Classifier: Development Status :: 3 - Alpha
Classifier: Environment :: Console
Classifier: Intended Audience :: Developers
Classifier: License :: OSI Approved :: GNU Library or Lesser General Public License (LGPL)
Classifier: Topic :: Utilities
